tonita/__init__.py
tonita/constants.py
tonita/errors.py
tonita/split_listing_batch.py
tonita/api/__init__.py
tonita/api/_helpers.py
tonita/api/add_scrap.py
tonita/api/corpora.py
tonita/api/eval.py
tonita/api/feedback.py
tonita/api/listings.py
tonita/api/search.py
tonita/datatypes/__init__.py
tonita/datatypes/corpora.py
tonita/datatypes/eval.py
tonita/datatypes/feedback.py
tonita/datatypes/listings.py
tonita/datatypes/search.py
tonita-0.0.9.dist-info/METADATA
tonita-0.0.9.dist-info/WHEEL
tonita-0.0.9.dist-info/top_level.txt
tonita-0.0.9.dist-info/RECORD
