Metadata-Version: 2.1
Name: tonita
Version: 0.0.9
Summary: Tonita Python Client Package
Author-email: Tonita <hello@tonita.co>
Project-URL: Homepage, https://www.tonita.co/
Classifier: Programming Language :: Python :: 3
Classifier: Operating System :: OS Independent
Requires-Python: >=3.9
Requires-Dist: requests ==2.31.0
Requires-Dist: rich ==12.5.1
Requires-Dist: urllib3 ==2.0.4
